odoo10_addon_crm_timesheet-10.0.2.0.0-py2.7-nspkg.pth
odoo/addons/crm_timesheet/README.rst
odoo/addons/crm_timesheet/__init__.py
odoo/addons/crm_timesheet/__manifest__.py
odoo/addons/crm_timesheet/i18n/es.po
odoo/addons/crm_timesheet/i18n/fr.po
odoo/addons/crm_timesheet/models/__init__.py
odoo/addons/crm_timesheet/models/account_analytic_line.py
odoo/addons/crm_timesheet/models/crm_lead.py
odoo/addons/crm_timesheet/static/description/icon.png
odoo/addons/crm_timesheet/tests/__init__.py
odoo/addons/crm_timesheet/tests/test_account_analytic_line.py
odoo/addons/crm_timesheet/views/crm_lead_view.xml
odoo/addons/crm_timesheet/views/hr_timesheet_view.xml
odoo10_addon_crm_timesheet-10.0.2.0.0.dist-info/DESCRIPTION.rst
odoo10_addon_crm_timesheet-10.0.2.0.0.dist-info/METADATA
odoo10_addon_crm_timesheet-10.0.2.0.0.dist-info/RECORD
odoo10_addon_crm_timesheet-10.0.2.0.0.dist-info/WHEEL
odoo10_addon_crm_timesheet-10.0.2.0.0.dist-info/metadata.json
odoo10_addon_crm_timesheet-10.0.2.0.0.dist-info/namespace_packages.txt
odoo10_addon_crm_timesheet-10.0.2.0.0.dist-info/top_level.txt
